jarvis_model/__init__.py
jarvis_model/errors.py
jarvis_model/flow.py
jarvis_model/jsonschema.py
jarvis_model/schemas.py
jarvis_model/tool_contracts.py
jarvis_model/validation.py
jarvis_model/version.py
jarvis_model-0.1.0a5.dist-info/licenses/LICENSE
jarvis_model-0.1.0a5.dist-info/METADATA
jarvis_model-0.1.0a5.dist-info/WHEEL
jarvis_model-0.1.0a5.dist-info/top_level.txt
jarvis_model-0.1.0a5.dist-info/RECORD
