Metadata-Version: 2.4
Name: jarvis-model
Version: 0.1.0a5
Summary: Shared, versioned data model and schemas for ARP components.
Author: Agent Runtime Protocol
License: MIT License
Project-URL: Repository, https://github.com/AgentRuntimeProtocol/JARVIS_Runtime_Model
Project-URL: Issues, https://github.com/AgentRuntimeProtocol/JARVIS_Runtime_Model/issues
Requires-Python: >=3.10
License-File: LICENSE
Provides-Extra: dev
Requires-Dist: pyright>=1.1.0; extra == "dev"
Requires-Dist: pytest>=7; extra == "dev"
Requires-Dist: pytest-cov>=4; extra == "dev"
Dynamic: license-file
